merakitools/__init__.py
merakitools/_metadata.py
merakitools/const.py
merakitools/getEvents.py
merakitools/main.py
merakitools/adp/__init__.py
merakitools/adp/db.py
merakitools/adp/main.py
merakitools/adp/models/__init__.py
merakitools/adp/models/adp.py
merakitools/adp/models/util_sqlalchemy.py
merakitools/adp/utils/__init__.py
merakitools/adp/utils/_getorginizations.py
merakitools/adp/utils/_orgprocces.py
merakitools/adp/utils/clean.py
merakitools/adp/utils/clone.py
merakitools/adp/utils/sync.py
merakitools/adp/utils/util_datetime.py
merakitools/api/__init__.py
merakitools/api/fifo.py
merakitools/api/server.py
merakitools/api/start.py
merakitools/app_logger/__init__.py
merakitools/app_logger/app_logger_setup.py
merakitools/app_logger/bcolors.py
merakitools/app_logger/fifo.py
merakitools/cli/__init__.py
merakitools/cli/cli.py
merakitools/cli/commands/__init__.py
merakitools/cli/commands/cmd_adp.py
merakitools/cli/commands/cmd_api.py
merakitools/cli/commands/cmd_device.py
merakitools/cli/commands/cmd_export.py
merakitools/cli/commands/cmd_switch.py
merakitools/cli/commands/cmd_sync.py
merakitools/devices/__init__.py
merakitools/devices/devices.py
merakitools/lib/__init__.py
merakitools/lib/bcolors.py
merakitools/lib/cache.py
merakitools/lib/find.py
merakitools/lib/helpers.py
merakitools/lib/meraki_addons.py
merakitools/lib/merakiapi.py
merakitools/lib/netcompare.py
merakitools/lib/printer.py
merakitools/meraki_tasks/__init__.py
merakitools/meraki_tasks/device_config.py
merakitools/meraki_tasks/sync.py
merakitools/mnetutils/__init__.py
merakitools/mnetutils/clone.py
merakitools/mnetutils/resync.py
merakitools/mnetutils/setup_orgs.py
merakitools/mnetutils/sync.py
merakitools/mnetutils/test_wireless.py
merakitools/model/__init__.py
merakitools/model/adp.py
merakitools/model/appconfig.py
merakitools/model/config_tag_manager.py
merakitools/model/device.py
merakitools/model/meraki.py
merakitools/model/mnet.py
merakitools/model/orgs.py
merakitools/model/overrides.py
Meraki_Tools-2.5.dist-info/LICENSE.txt
Meraki_Tools-2.5.dist-info/METADATA
Meraki_Tools-2.5.dist-info/WHEEL
Meraki_Tools-2.5.dist-info/entry_points.txt
Meraki_Tools-2.5.dist-info/top_level.txt
Meraki_Tools-2.5.dist-info/RECORD
