Metadata-Version: 2.1
Name: Meraki-Tools
Version: 2.5
Summary: Meraki Tools is a system that can either run from the CLI or as a webserver that will receive API calls to run sync functionas agains mulitapl meraki orginizationsPlease use the new enverment variable to set the config file location MERAKI_TOOLS_CONFIG=/path/to-config-file
Home-page: UNKNOWN
Author: Josh Lipton
Author-email: joliptn@cisco.com
License: UNKNOWN
Platform: UNKNOWN
Requires-Dist: aiohttp
Requires-Dist: async-timeout
Requires-Dist: attrs
Requires-Dist: bcolors
Requires-Dist: certifi
Requires-Dist: chardet
Requires-Dist: idna
Requires-Dist: meraki
Requires-Dist: multidict
Requires-Dist: requests
Requires-Dist: typing-extensions
Requires-Dist: urllib3
Requires-Dist: yarl
Requires-Dist: http3
Requires-Dist: click
Requires-Dist: pandas
Requires-Dist: tabulate
Requires-Dist: python-dateutil
Requires-Dist: automodinit
Requires-Dist: python-dotenv
Requires-Dist: wheel
Requires-Dist: deepdiff
Requires-Dist: jsonpickle
Requires-Dist: viptela
Requires-Dist: flask
Requires-Dist: werkzeug
Requires-Dist: flask-restful
Requires-Dist: flask-jwt-extended
Requires-Dist: sqlalchemy
